eon_collective_docs_theme/__init__.py
eon_collective_docs_theme/breadcrumbs.html
eon_collective_docs_theme/domainindex.html
eon_collective_docs_theme/extensions.html
eon_collective_docs_theme/footer.html
eon_collective_docs_theme/genindex-single.html
eon_collective_docs_theme/genindex-split.html
eon_collective_docs_theme/genindex.html
eon_collective_docs_theme/globaltoc.html
eon_collective_docs_theme/layout.html
eon_collective_docs_theme/page.html
eon_collective_docs_theme/pager.html
eon_collective_docs_theme/search.html
eon_collective_docs_theme/searchbox.html
eon_collective_docs_theme/searchresults.html
eon_collective_docs_theme/sitemap.html
eon_collective_docs_theme/source-buttons.html
eon_collective_docs_theme/theme.conf
eon_collective_docs_theme/dist/UNKNOWN-0.0.0.tar.gz
eon_collective_docs_theme/static/dist/blocking.js
eon_collective_docs_theme/static/dist/blocking.js.map
eon_collective_docs_theme/static/dist/fontawesome.css
eon_collective_docs_theme/static/dist/fontawesome.css.map
eon_collective_docs_theme/static/dist/fontawesome.js
eon_collective_docs_theme/static/dist/fontawesome.js.map
eon_collective_docs_theme/static/dist/theme.css
eon_collective_docs_theme/static/dist/theme.css.map
eon_collective_docs_theme/static/dist/theme.js
eon_collective_docs_theme/static/dist/theme.js.map
eon_collective_docs_theme/static/dist/vendor.js
eon_collective_docs_theme/static/dist/vendor.js.map
eon_collective_docs_theme/static/dist/assets/fa-brands-400.eot
eon_collective_docs_theme/static/dist/assets/fa-brands-400.svg
eon_collective_docs_theme/static/dist/assets/fa-brands-400.ttf
eon_collective_docs_theme/static/dist/assets/fa-brands-400.woff
eon_collective_docs_theme/static/dist/assets/fa-brands-400.woff2
eon_collective_docs_theme/static/dist/assets/fa-regular-400.eot
eon_collective_docs_theme/static/dist/assets/fa-regular-400.svg
eon_collective_docs_theme/static/dist/assets/fa-regular-400.ttf
eon_collective_docs_theme/static/dist/assets/fa-regular-400.woff
eon_collective_docs_theme-0.0.2.dev0.dist-info/LICENSE
eon_collective_docs_theme-0.0.2.dev0.dist-info/METADATA
eon_collective_docs_theme-0.0.2.dev0.dist-info/WHEEL
eon_collective_docs_theme-0.0.2.dev0.dist-info/top_level.txt
eon_collective_docs_theme-0.0.2.dev0.dist-info/RECORD
