Metadata-Version: 2.1
Name: eon-collective-docs-theme
Version: 0.0.2.dev0
Summary: The theme used to render documentation
Home-page: https://github.com/janerose-njogu/eon-collective-docs-theme
Author: Janerose Njogu
Author-email: janerose.njogu@eoncllective.com
Classifier: Framework :: Sphinx
Classifier: Framework :: Sphinx :: Theme
Classifier: Development Status :: 3 - Alpha
Classifier: License :: OSI Approved :: MIT License
Classifier: Intended Audience :: Developers
Classifier: Programming Language :: Python :: 3.8
Classifier: Programming Language :: Python :: 3.9
Classifier: Programming Language :: Python :: 3.10
Classifier: Programming Language :: Python :: 3.11
Classifier: Operating System :: OS Independent
Classifier: Topic :: Documentation
Classifier: Topic :: Software Development :: Documentation
Requires-Python: >=3.8
License-File: LICENSE
